README.md
setup.cfg
setup.py
distributions_gaussian_binomial_ml_course/Binomialdistribution.py
distributions_gaussian_binomial_ml_course/Gaussiandistribution.py
distributions_gaussian_binomial_ml_course/Generaldistribution.py
distributions_gaussian_binomial_ml_course/__init__.py
distributions_gaussian_binomial_ml_course.egg-info/PKG-INFO
distributions_gaussian_binomial_ml_course.egg-info/SOURCES.txt
distributions_gaussian_binomial_ml_course.egg-info/dependency_links.txt
distributions_gaussian_binomial_ml_course.egg-info/not-zip-safe
distributions_gaussian_binomial_ml_course.egg-info/top_level.txt