Metadata-Version: 1.0
Name: distributions-gaussian-binomial-ml-course
Version: 0.1
Summary: Gaussian and Binomial distributions_ml_course
Home-page: UNKNOWN
Author: jramirezc
Author-email: UNKNOWN
License: UNKNOWN
Platform: UNKNOWN
